{
  "id": "company:4:34143c6a-6a1b-4864-a68e-0d38c967b901:273422",
  "title": "MUNICIPIO DE VILLETA",
  "subtitle": "Empresa · 8999993122",
  "summary": "La empresa comparte dirección o control con persona(s) que también aparecen en registros activos de cargo o salario público.",
  "tags": [
    "Proveedor con directivo o vínculo en cargo público"
  ],
  "public_sources": [],
  "graph": {
    "center_id": "company:4:34143c6a-6a1b-4864-a68e-0d38c967b901:273422",
    "nodes": [
      {
        "id": "company:4:34143c6a-6a1b-4864-a68e-0d38c967b901:273422",
        "label": "MUNICIPIO DE VILLETA",
        "type": "company",
        "properties": {
          "risk_score": 10,
          "signal_types": 3,
          "contract_count": 143,
          "contract_value": 30921089396.0
        },
        "sources": [],
        "is_pep": false,
        "exposure_tier": "public_safe",
        "document_id": "8999993122"
      },
      {
        "id": "company:4:34143c6a-6a1b-4864-a68e-0d38c967b901:273422:official:1",
        "label": "JHON ALEXANDER MORERA GUTIERREZ",
        "type": "person",
        "properties": {},
        "sources": [],
        "is_pep": false,
        "exposure_tier": "public_safe"
      },
      {
        "id": "company:4:34143c6a-6a1b-4864-a68e-0d38c967b901:273422:contracts",
        "label": "Contratos detectados (143)",
        "type": "contract",
        "properties": {
          "contract_count": 143,
          "total_value": 30921089396.0
        },
        "sources": [],
        "is_pep": false,
        "exposure_tier": "public_safe"
      }
    ],
    "edges": [
      {
        "source": "company:4:34143c6a-6a1b-4864-a68e-0d38c967b901:273422:official:1",
        "target": "company:4:34143c6a-6a1b-4864-a68e-0d38c967b901:273422",
        "type": "OFFICER_OF",
        "confidence": 1.0,
        "properties": {
          "match_reason": "watchlist_overlap"
        }
      },
      {
        "source": "company:4:34143c6a-6a1b-4864-a68e-0d38c967b901:273422:contracts",
        "target": "company:4:34143c6a-6a1b-4864-a68e-0d38c967b901:273422",
        "type": "CONTRATOU",
        "confidence": 1.0,
        "properties": {
          "contract_count": 143,
          "total_value": 30921089396.0
        }
      }
    ]
  }
}
